mezcla/TODO.md
mezcla/__init__.py
mezcla/__main__.py
mezcla/audio.py
mezcla/bash_ast.py
mezcla/bing_search.py
mezcla/check_html_javascript.py
mezcla/compute_tfidf.py
mezcla/convert_emoticons.py
mezcla/cut.py
mezcla/data_utils.py
mezcla/debug.py
mezcla/evaluate_example_tests.py
mezcla/extract_document_text.py
mezcla/file_utils.py
mezcla/filter_random.py
mezcla/format_profile.py
mezcla/gensim_test.py
mezcla/glue_helpers.py
mezcla/google_word2vec.py
mezcla/gpu_utils.py
mezcla/html_utils.py
mezcla/introspection.py
mezcla/ipython_utils.py
mezcla/kenlm_example.py
mezcla/keras_param_search.py
mezcla/llm_desktop_search.py
mezcla/main.py
mezcla/master_test.py
mezcla/merge_files.py
mezcla/merge_notes.py
mezcla/mezcla
mezcla/mezcla_to_standard.py
mezcla/misc_utils.py
mezcla/my_regex.py
mezcla/ngram_tfidf.py
mezcla/os_utils.py
mezcla/pandas_sklearn.py
mezcla/plot_utils.py
mezcla/poe_client.py
mezcla/python_ast.py
mezcla/randomize_lines.py
mezcla/rgb_color_name.py
mezcla/simple_main_example.py
mezcla/spacy_nlp.py
mezcla/spell.py
mezcla/summarize_pytest.py
mezcla/system.py
mezcla/template.py
mezcla/text_categorizer.py
mezcla/text_processing.py
mezcla/text_utils.py
mezcla/tpo_common.py
mezcla/train_language_model.py
mezcla/train_text_categorizer.py
mezcla/transpose_data.py
mezcla/unittest_wrapper.py
mezcla/validate_arguments.py
mezcla/validate_arguments_types.py
mezcla/xml_utils.py
mezcla/adhoc/__init__.py
mezcla/adhoc/check_time_tracking.py
mezcla/adhoc/perform_regression.py
mezcla/adhoc/tests/__init__.py
mezcla/adhoc/tests/test_check_time_tracking.py
mezcla/adhoc/tests/test_perform_regression.py
mezcla/archive/analyze_tfidf.py
mezcla/archive/bert_multi_classification.py
mezcla/archive/bert_text_classification.py
mezcla/archive/run_albert_classifier.py
mezcla/archive/run_bert_classifier.py
mezcla/archive/search_table_file_index.py
mezcla/archive/show_bert_representation.py
mezcla/archive/sys_version_info_hack.py
mezcla/archive/tests/__init__.py
mezcla-1.4.0.7.dist-info/LICENSE.txt
mezcla-1.4.0.7.dist-info/WHEEL
mezcla-1.4.0.7.dist-info/METADATA
mezcla-1.4.0.7.dist-info/RECORD
