Metadata-Version: 2.3
Name: mezcla
Version: 1.4.0.7
Summary: Mezcla is Spanish for mixture, and this repository contains a variety of Python scripts.
Home-page: https://github.com/tomasohara/mezcla
License: LGPLv3
Author: Tomás O'Hara
Author-email: tomasohara@gmail.com
